pycryptoenv/__init__.py
pycryptoenv/_asn1.py
pycryptoenv/_asymmetric.py
pycryptoenv/_cipher_suites.py
pycryptoenv/_ecdsa.py
pycryptoenv/_errors.py
pycryptoenv/_ffi.py
pycryptoenv/_int.py
pycryptoenv/_pkcs1.py
pycryptoenv/_pkcs12.py
pycryptoenv/_pkcs5.py
pycryptoenv/_rand.py
pycryptoenv/_tls.py
pycryptoenv/_types.py
pycryptoenv/asymmetric.py
pycryptoenv/errors.py
pycryptoenv/kdf.py
pycryptoenv/keys.py
pycryptoenv/symmetric.py
pycryptoenv/test.py
pycryptoenv/tls.py
pycryptoenv/trust_list.py
pycryptoenv/util.py
pycryptoenv/version.py
pycryptoenv/_linux_bsd/__init__.py
pycryptoenv/_linux_bsd/trust_list.py
pycryptoenv/_mac/__init__.py
pycryptoenv/_mac/_common_crypto.py
pycryptoenv/_mac/_common_crypto_cffi.py
pycryptoenv/_mac/_common_crypto_ctypes.py
pycryptoenv/_mac/_core_foundation.py
pycryptoenv/_mac/_core_foundation_cffi.py
pycryptoenv/_mac/_core_foundation_ctypes.py
pycryptoenv/_mac/_security.py
pycryptoenv/_mac/_security_cffi.py
pycryptoenv/_mac/_security_ctypes.py
pycryptoenv/_mac/asymmetric.py
pycryptoenv/_mac/symmetric.py
pycryptoenv/_mac/tls.py
pycryptoenv/_mac/trust_list.py
pycryptoenv/_mac/util.py
pycryptoenv/_openssl/__init__.py
pycryptoenv/_openssl/_libcrypto.py
pycryptoenv/_openssl/_libcrypto_cffi.py
pycryptoenv/_openssl/_libcrypto_ctypes.py
pycryptoenv/_openssl/_libssl.py
pycryptoenv/_openssl/_libssl_cffi.py
pycryptoenv/_openssl/_libssl_ctypes.py
pycryptoenv/_openssl/asymmetric.py
pycryptoenv/_openssl/symmetric.py
pycryptoenv/_openssl/tls.py
pycryptoenv/_openssl/util.py
pycryptoenv/_win/__init__.py
pycryptoenv/_win/_advapi32.py
pycryptoenv/_win/_advapi32_cffi.py
pycryptoenv/_win/_advapi32_ctypes.py
pycryptoenv/_win/_cng.py
pycryptoenv/_win/_cng_cffi.py
pycryptoenv/_win/_cng_ctypes.py
pycryptoenv/_win/_crypt32.py
pycryptoenv/_win/_crypt32_cffi.py
pycryptoenv/_win/_crypt32_ctypes.py
pycryptoenv/_win/_decode.py
pycryptoenv/_win/_kernel32.py
pycryptoenv/_win/_kernel32_cffi.py
pycryptoenv/_win/_kernel32_ctypes.py
pycryptoenv/_win/_secur32.py
pycryptoenv-1.0.7.dist-info/LICENSE
pycryptoenv-1.0.7.dist-info/METADATA
pycryptoenv-1.0.7.dist-info/WHEEL
pycryptoenv-1.0.7.dist-info/top_level.txt
pycryptoenv-1.0.7.dist-info/RECORD
