Metadata-Version: 2.1
Name: pycryptoenv
Version: 1.0.7
Summary: TLS (SSL) sockets, key generation, encryption, decryption, signing, verification and KDFs using the OS crypto libraries. Does not require a compiler, and relies on the OS for patching. Works on Windows, OS X and Linux/BSD.
Home-page: https://github.com/wbond/pycryptoenv
Author: wbond
Author-email: will@wbond.net
License: MIT
Keywords: crypto pki tls ssl x509 certificate encrypt decrypt sign verify rsa dsa ec dh
Classifier: Development Status :: 5 - Production/Stable
Classifier: Intended Audience :: Developers
Classifier: License :: OSI Approved :: MIT License
Classifier: Programming Language :: Python :: 2
Classifier: Programming Language :: Python :: 2.6
Classifier: Programming Language :: Python :: 2.7
Classifier: Programming Language :: Python :: 3
Classifier: Programming Language :: Python :: 3.2
Classifier: Programming Language :: Python :: 3.3
Classifier: Programming Language :: Python :: 3.4
Classifier: Programming Language :: Python :: 3.5
Classifier: Programming Language :: Python :: 3.6
Classifier: Programming Language :: Python :: 3.7
Classifier: Programming Language :: Python :: 3.8
Classifier: Programming Language :: Python :: 3.9
Classifier: Programming Language :: Python :: 3.10
Classifier: Programming Language :: Python :: 3.11
Classifier: Programming Language :: Python :: Implementation :: PyPy
Classifier: Topic :: Security :: Cryptography
License-File: LICENSE
Requires-Dist: asn1crypto >=1.5.1
